main/__init__.py
setch-0.0.1.dist-info/METADATA
setch-0.0.1.dist-info/WHEEL
setch-0.0.1.dist-info/top_level.txt
setch-0.0.1.dist-info/RECORD
